GitiPack/__init__.py
GitiPack/tig.py
GitiPack-1.7.0.dist-info/LICENSE
GitiPack-1.7.0.dist-info/METADATA
GitiPack-1.7.0.dist-info/WHEEL
GitiPack-1.7.0.dist-info/top_level.txt
GitiPack-1.7.0.dist-info/RECORD
