Metadata-Version: 2.1
Name: GitiPack
Version: 1.7.0
Summary: GITI网站的辅助功能，用于推动GITI的发展
Home-page: https://github.com/ljy-002/GitiPack
Author: Tig-ljy
Author-email: ljy123ljy123@dingtalk.com
License: UNKNOWN
Platform: UNKNOWN
Classifier: Programming Language :: Python :: 3.7
Classifier: License :: OSI Approved :: MIT License
Classifier: Operating System :: OS Independent
Requires-Python: >=3.7
Provides-Extra: gitipack
Requires-Dist: python ; extra == 'gitipack'
